{
	"type" : "FeatureCollection",
	"features" : [
		{
			"type" : "Feature",
			"properties" : {
				
			},
			"geometry" : {
				"city" : "Gdańsk",
				"type" : "Point",
				"coordinates" : [
					18.59567,
					54.3509
				]
			}
		},
		{
			"type" : "Feature",
			"properties" : {
				
			},
			"geometry" : {
				"city" : "Gdańsk",
				"type" : "Point",
				"coordinates" : [
					18.71147,
					54.3506
				]
			}
		},
		{
			"type" : "Feature",
			"properties" : {
				
			},
			"geometry" : {
				"city" : "Gdańsk",
				"type" : "Point",
				"coordinates" : [
					18.65841,
					54.391505
				]
			}
		},
		{
			"type" : "Feature",
			"properties" : {
				
			},
			"geometry" : {
				"city" : "Gdańsk",
				"type" : "Point",
				"coordinates" : [
					18.571749,
					54.337487
				]
			}
		},
		{
			"type" : "Feature",
			"properties" : {
				
			},
			"geometry" : {
				"city" : "Gdańsk",
				"type" : "Point",
				"coordinates" : [
					18.619926,
					54.394374
				]
			}
		},
		{
			"type" : "Feature",
			"properties" : {
				
			},
			"geometry" : {
				"city" : "Gdańsk",
				"type" : "Point",
				"coordinates" : [
					18.621572,
					54.397784
				]
			}
		},
		{
			"type" : "Feature",
			"properties" : {
				
			},
			"geometry" : {
				"city" : "Gdańsk",
				"type" : "Point",
				"coordinates" : [
					18.59482,
					54.40933
				]
			}
		},
		{
			"type" : "Feature",
			"properties" : {
				
			},
			"geometry" : {
				"city" : "Gdańsk",
				"type" : "Point",
				"coordinates" : [
					18.52591,
					54.35009
				]
			}
		},
		{
			"type" : "Feature",
			"properties" : {
				
			},
			"geometry" : {
				"city" : "Kowale",
				"type" : "Point",
				"coordinates" : [
					18.546702,
					54.304205
				]
			}
		},
		{
			"type" : "Feature",
			"properties" : {
				
			},
			"geometry" : {
				"city" : "Straszyn",
				"type" : "Point",
				"coordinates" : [
					18.59435,
					54.27803
				]
			}
		},
		{
			"type" : "Feature",
			"properties" : {
				
			},
			"geometry" : {
				"city" : "Pruszcz Gdański",
				"type" : "Point",
				"coordinates" : [
					18.610153,
					54.24019
				]
			}
		},
		{
			"type" : "Feature",
			"properties" : {
				
			},
			"geometry" : {
				"city" : "Gdańsk",
				"type" : "Point",
				"coordinates" : [
					18.435228,
					54.382705
				]
			}
		},
		{
			"type" : "Feature",
			"properties" : {
				
			},
			"geometry" : {
				"city" : "Gdynia",
				"type" : "Point",
				"coordinates" : [
					18.535432,
					54.492022
				]
			}
		},
		{
			"type" : "Feature",
			"properties" : {
				
			},
			"geometry" : {
				"city" : "Gdynia",
				"type" : "Point",
				"coordinates" : [
					18.480598,
					54.472753
				]
			}
		},
		{
			"type" : "Feature",
			"properties" : {
				
			},
			"geometry" : {
				"city" : "Gdynia",
				"type" : "Point",
				"coordinates" : [
					18.47884,
					54.47279
				]
			}
		},
		{
			"type" : "Feature",
			"properties" : {
				
			},
			"geometry" : {
				"city" : "Żukowo",
				"type" : "Point",
				"coordinates" : [
					18.375503,
					54.353355
				]
			}
		},
		{
			"type" : "Feature",
			"properties" : {
				
			},
			"geometry" : {
				"city" : "Gdynia",
				"type" : "Point",
				"coordinates" : [
					18.53477,
					54.49703
				]
			}
		},
		{
			"type" : "Feature",
			"properties" : {
				
			},
			"geometry" : {
				"city" : "Gdynia",
				"type" : "Point",
				"coordinates" : [
					18.51422,
					54.49651
				]
			}
		}
	]
}